plotool/RealtimeDrawing.py
plotool/__init__.py
plotool-0.0.5.dist-info/METADATA
plotool-0.0.5.dist-info/WHEEL
plotool-0.0.5.dist-info/top_level.txt
plotool-0.0.5.dist-info/RECORD
