Metadata-Version: 2.1
Name: plotool
Version: 0.0.5
Summary: Useful tools for plotting
Author: Xinlin Wang
Author-email: wangxinlin525@gmail.com
Keywords: python,plot
Classifier: Development Status :: 3 - Alpha
Classifier: Intended Audience :: Education
Classifier: Programming Language :: Python :: 2
Classifier: Programming Language :: Python :: 3
Classifier: Operating System :: MacOS :: MacOS X
Classifier: Operating System :: Microsoft :: Windows
Requires-Dist: matplotlib
